jax_autovmap.py
test_autovmap.py
jax_autovmap-0.3.0.dist-info/METADATA
jax_autovmap-0.3.0.dist-info/WHEEL
jax_autovmap-0.3.0.dist-info/top_level.txt
jax_autovmap-0.3.0.dist-info/RECORD
