Metadata-Version: 2.4
Name: jax_autovmap
Version: 0.3.0
Summary: Automatically broadcast inputs by dynamically applying jax.vmap given un-batched argument dimensions.
Author-email: Mathis Gerdes <mathisgerdes@gmail.com>
Classifier: Programming Language :: Python :: 3
Classifier: License :: OSI Approved :: MIT License
Classifier: Operating System :: OS Independent
Requires-Python: >=3.8
Requires-Dist: jax>=0.4.1
Requires-Dist: numpy
